<?xml version="1.0" encoding="UTF-8"?>
<naeringsspesifikasjon
    xmlns="urn:no:skatteetaten:fastsetting:formueinntekt:naeringsspesifikasjon:ekstern:v5">
    <partsreferanse>1442927932</partsreferanse>
    <inntektsaar>2024</inntektsaar>
    <resultatregnskap>
        <driftsinntekt>
            <sumDriftsinntekt>
                <beloep>
                    <beloep>1587535</beloep>
                </beloep>
            </sumDriftsinntekt>
            <salgsinntekt>
                <inntekt>
                    <beloep>
                        <beloep>
                            <beloep>1587535</beloep>
                        </beloep>
                    </beloep>
                    <id>3000</id>
                    <type>
                        <resultatOgBalanseregnskapstype>3000</resultatOgBalanseregnskapstype>
                    </type>
                </inntekt>
            </salgsinntekt>
        </driftsinntekt>
        <driftskostnad>
            <sumDriftskostnad>
                <beloep>
                    <beloep>1118032</beloep>
                </beloep>
            </sumDriftskostnad>
            <annenDriftskostnad>
                <kostnad>
                    <beloep>
                        <beloep>
                            <beloep>1118032</beloep>
                        </beloep>
                    </beloep>
                    <id>6000</id>
                    <type>
                        <resultatOgBalanseregnskapstype>6000</resultatOgBalanseregnskapstype>
                    </type>
                </kostnad>
            </annenDriftskostnad>
        </driftskostnad>
        <sumFinansinntekt>
            <beloep>
                <beloep>25586</beloep>
            </beloep>
        </sumFinansinntekt>
        <sumFinanskostnad>
            <beloep>
                <beloep>1682</beloep>
            </beloep>
        </sumFinanskostnad>
        <sumSkattekostnad>
            <beloep>
                <beloep>108549</beloep>
            </beloep>
        </sumSkattekostnad>
        <finansinntekt>
            <inntekt>
                <beloep>
                    <beloep>
                        <beloep>25586</beloep>
                    </beloep>
                </beloep>
                <id>8050</id>
                <type>
                    <resultatOgBalanseregnskapstype>8050</resultatOgBalanseregnskapstype>
                </type>
            </inntekt>
        </finansinntekt>
        <finanskostnad>
            <kostnad>
                <beloep>
                    <beloep>
                        <beloep>1682</beloep>
                    </beloep>
                </beloep>
                <id>8115</id>
                <type>
                    <resultatOgBalanseregnskapstype>8115</resultatOgBalanseregnskapstype>
                </type>
            </kostnad>
        </finanskostnad>
        <skattekostnad>
            <kostnad>
                <beloep>
                    <beloep>
                        <beloep>108549</beloep>
                    </beloep>
                </beloep>
                <id>8300</id>
                <type>
                    <resultatOgBalanseregnskapstype>8300</resultatOgBalanseregnskapstype>
                </type>
            </kostnad>
        </skattekostnad>
        <aarsresultat>
            <beloep>
                <beloep>384858</beloep>
            </beloep>
        </aarsresultat>
    </resultatregnskap>
    <balanseregnskap>
        <omloepsmiddel>
            <sumBalanseverdiForOmloepsmiddel>
                <beloep>
                    <beloep>1312556</beloep>
                </beloep>
            </sumBalanseverdiForOmloepsmiddel>
            <balanseverdiForOmloepsmiddel>
                <balanseverdi>
                    <id>1900</id>
                    <beloep>
                        <beloep>
                            <beloep>1312556</beloep>
                        </beloep>
                    </beloep>
                    <type>
                        <resultatOgBalanseregnskapstype>1900</resultatOgBalanseregnskapstype>
                    </type>
                    <ekskluderesFraSkattemeldingen>
                        <boolsk>true</boolsk>
                    </ekskluderesFraSkattemeldingen>
                </balanseverdi>
            </balanseverdiForOmloepsmiddel>
        </omloepsmiddel>
        <gjeldOgEgenkapital>
            <sumKortsiktigGjeld>
                <beloep>
                    <beloep>983291</beloep>
                </beloep>
            </sumKortsiktigGjeld>
            <sumEgenkapital>
                <beloep>
                    <beloep>329265</beloep>
                </beloep>
            </sumEgenkapital>
            <kortsiktigGjeld>
                <gjeld>
                    <id>2400</id>
                    <beloep>
                        <beloep>
                            <beloep>983291</beloep>
                        </beloep>
                    </beloep>
                    <type>
                        <resultatOgBalanseregnskapstype>2400</resultatOgBalanseregnskapstype>
                    </type>
                    <ekskluderesFraSkattemeldingen>
                        <boolsk>true</boolsk>
                    </ekskluderesFraSkattemeldingen>
                </gjeld>
            </kortsiktigGjeld>
            <egenkapital>
                <kapital>
                    <id>2050</id>
                    <beloep>
                        <beloep>
                            <beloep>329265</beloep>
                        </beloep>
                    </beloep>
                    <type>
                        <resultatOgBalanseregnskapstype>2050</resultatOgBalanseregnskapstype>
                    </type>
                </kapital>
            </egenkapital>
        </gjeldOgEgenkapital>
        <sumBalanseverdiForEiendel>
            <beloep>
                <beloep>1312556</beloep>
            </beloep>
        </sumBalanseverdiForEiendel>
        <sumGjeldOgEgenkapital>
            <beloep>
                <beloep>1312556</beloep>
            </beloep>
        </sumGjeldOgEgenkapital>
    </balanseregnskap>
    <beregnetNaeringsinntekt>
        <fordeltBeregnetNaeringsinntektForUpersonligSkattepliktig>
            <id>h1</id>
            <kommunenummer>
                <kommunenummer>5001</kommunenummer>
            </kommunenummer>
            <fordeltSkattemessigResultat>
                <beloep>
                    <beloep>493407</beloep>
                </beloep>
            </fordeltSkattemessigResultat>
            <fordeltSkattemessigResultatEtterKorreksjon>
                <beloep>
                    <beloep>493407</beloep>
                </beloep>
            </fordeltSkattemessigResultatEtterKorreksjon>
        </fordeltBeregnetNaeringsinntektForUpersonligSkattepliktig>
        <skattemessigResultat>
            <beloep>
                <beloep>493407</beloep>
            </beloep>
        </skattemessigResultat>
    </beregnetNaeringsinntekt>
    <forskjellMellomRegnskapsmessigOgSkattemessigVerdi>
        <permanentForskjell>
            <id>1</id>
            <permanentForskjellstype>
                <permanentForskjellstype>positivSkattekostnad</permanentForskjellstype>
            </permanentForskjellstype>
            <beloep>
                <beloep>
                    <beloep>108549</beloep>
                </beloep>
            </beloep>
        </permanentForskjell>
        <sumTilleggINaeringsinntekt>
            <beloep>
                <beloep>108549</beloep>
            </beloep>
        </sumTilleggINaeringsinntekt>
    </forskjellMellomRegnskapsmessigOgSkattemessigVerdi>
    <virksomhet>
        <regnskapspliktstype>
            <regnskapspliktstype>fullRegnskapsplikt</regnskapspliktstype>
        </regnskapspliktstype>
        <regnskapsperiode>
            <start><dato>2024-01-01</dato></start>
            <slutt><dato>2024-12-31</dato></slutt>
        </regnskapsperiode>
        <virksomhetstype>
            <virksomhetstype>oevrigSelskap</virksomhetstype>
        </virksomhetstype>
        <regeltypeForAarsregnskap>
            <regeltypeForAarsregnskap>regnskapslovensAlminneligeRegler</regeltypeForAarsregnskap>
        </regeltypeForAarsregnskap>
    </virksomhet>
    <egenkapitalavstemming>
        <inngaaendeEgenkapital>
            <beloep>
                <beloep>314407</beloep>
            </beloep>
        </inngaaendeEgenkapital>
        <sumTilleggIEgenkapital>
            <beloep>
                <beloep>384858</beloep>
            </beloep>
        </sumTilleggIEgenkapital>
        <sumFradragIEgenkapital>
            <beloep>
                <beloep>400000</beloep>
            </beloep>
        </sumFradragIEgenkapital>
        <egenkapitalendring>
            <id>EK1</id>
            <egenkapitalendringstype>
                <egenkapitalendringstype>aaretsOverskudd</egenkapitalendringstype>
            </egenkapitalendringstype>
            <beloep>
                <beloep>
                    <beloep>384858</beloep>
                </beloep>
            </beloep>
        </egenkapitalendring>
        <egenkapitalendring>
            <id>EK2</id>
            <egenkapitalendringstype>
                <egenkapitalendringstype>avsattEllerForventetUtbytte</egenkapitalendringstype>
            </egenkapitalendringstype>
            <beloep>
                <beloep>
                    <beloep>400000</beloep>
                </beloep>
            </beloep>
        </egenkapitalendring>
        <utgaaendeEgenkapital>
            <beloep>
                <beloep>299265</beloep>
            </beloep>
        </utgaaendeEgenkapital>
    </egenkapitalavstemming>
    <skalBekreftesAvRevisor>false</skalBekreftesAvRevisor>
</naeringsspesifikasjon>
